{"url": "https://api.github.com/repos/rust-lang/rust/pulls/68448", "id": 365700917, "node_id": "MDExOlB1bGxSZXF1ZXN0MzY1NzAwOTE3", "html_url": "https://github.com/rust-lang/rust/pull/68448", "diff_url": "https://github.com/rust-lang/rust/pull/68448.diff", "patch_url": "https://github.com/rust-lang/rust/pull/68448.patch", "issue_url": "https://api.github.com/repos/rust-lang/rust/issues/68448", "number": 68448, "state": "closed", "locked": false, "title": "rustc: Allow cdylibs to link against dylibs", "user": {"login": "maurer", "id": 136037, "node_id": "MDQ6VXNlcjEzNjAzNw==", "avatar_url": "https://avatars.githubusercontent.com/u/136037?v=4", "gravatar_id": "", "url": "https://api.github.com/users/maurer", "html_url": "https://github.com/maurer", "followers_url": "https://api.github.com/users/maurer/followers", "following_url": "https://api.github.com/users/maurer/following{/other_user}", "gists_url": "https://api.github.com/users/maurer/gists{/gist_id}", "starred_url": "https://api.github.com/users/maurer/starred{/owner}{/repo}", "subscriptions_url": "https://api.github.com/users/maurer/subscriptions", "organizations_url": "https://api.github.com/users/maurer/orgs", "repos_url": "https://api.github.com/users/maurer/repos", "events_url": "https://api.github.com/users/maurer/events{/privacy}", "received_events_url": "https://api.github.com/users/maurer/received_events", "type": "User", "site_admin": false}, "body": "Previously, rustc mandated that cdylibs could only link against rlibs as dependencies (not dylibs).\r\nThis commit disables that restriction and tests that it works in a simple case.\r\n\r\nI don't have a windows rustc dev environment, so I guessed at the MSVC test code, I'm hoping the CI can run that for me.\r\n\r\nAdditionally, we might want to consider emitting (through cargo or rustc) some metadata to help C users of a cdylib figure out where all the dylibs they need are. I don't think that should be needed to land this change, as it will still be usable by homogeneous build systems without it.\r\n\r\nMy new test was templated off the `tests/run-make-fulldeps/cdylib` test. It seemed more appropriate to have it as a separate test, since both foo.rs and bar.rs would need to be replicated to make that test cover both cases, but I can do that if it would be preferred.\r\n\r\nIf I'm doing anything out of order/process, please let me know; this is only my second change to rustc and the prior one was trivial.\r\n\r\nr? alexcrichton", "created_at": "2020-01-22T07:14:57Z", "updated_at": "2020-01-25T10:59:55Z", "closed_at": "2020-01-25T10:59:55Z", "merged_at": "2020-01-25T10:59:55Z", "merge_commit_sha": "72aaa3a414d17aa0c4f19feafa5bab5f84b60e63", "assignee": {"login": "alexcrichton", "id": 64996, "node_id": "MDQ6VXNlcjY0OTk2", "avatar_url": "https://avatars.githubusercontent.com/u/64996?v=4", "gravatar_id": "", "url": "https://api.github.com/users/alexcrichton", "html_url": "https://github.com/alexcrichton", "followers_url": "https://api.github.com/users/alexcrichton/followers", "following_url": "https://api.github.com/users/alexcrichton/following{/other_user}", "gists_url": "https://api.github.com/users/alexcrichton/gists{/gist_id}", "starred_url": "https://api.github.com/users/alexcrichton/starred{/owner}{/repo}", "subscriptions_url": "https://api.github.com/users/alexcrichton/subscriptions", "organizations_url": "https://api.github.com/users/alexcrichton/orgs", "repos_url": "https://api.github.com/users/alexcrichton/repos", "events_url": "https://api.github.com/users/alexcrichton/events{/privacy}", "received_events_url": "https://api.github.com/users/alexcrichton/received_events", "type": "User", "site_admin": false}, "assignees": [{"login": "alexcrichton", "id": 64996, "node_id": "MDQ6VXNlcjY0OTk2", "avatar_url": "https://avatars.githubusercontent.com/u/64996?v=4", "gravatar_id": "", "url": "https://api.github.com/users/alexcrichton", "html_url": "https://github.com/alexcrichton", "followers_url": "https://api.github.com/users/alexcrichton/followers", "following_url": "https://api.github.com/users/alexcrichton/following{/other_user}", "gists_url": "https://api.github.com/users/alexcrichton/gists{/gist_id}", "starred_url": "https://api.github.com/users/alexcrichton/starred{/owner}{/repo}", "subscriptions_url": "https://api.github.com/users/alexcrichton/subscriptions", "organizations_url": "https://api.github.com/users/alexcrichton/orgs", "repos_url": "https://api.github.com/users/alexcrichton/repos", "events_url": "https://api.github.com/users/alexcrichton/events{/privacy}", "received_events_url": "https://api.github.com/users/alexcrichton/received_events", "type": "User", "site_admin": false}], "requested_reviewers": [], "requested_teams": [], "labels": [{"id": 583437191, "node_id": "MDU6TGFiZWw1ODM0MzcxOTE=", "url": "https://api.github.com/repos/rust-lang/rust/labels/S-waiting-on-bors", "name": "S-waiting-on-bors", "color": "d3dddd", "default": false, "description": "Status: Waiting on bors to run and complete tests. Bors will change the label on completion."}, {"id": 1223998418, "node_id": "MDU6TGFiZWwxMjIzOTk4NDE4", "url": "https://api.github.com/repos/rust-lang/rust/labels/merged-by-bors", "name": "merged-by-bors", "color": "dae4e4", "default": false, "description": "This PR was explicitly merged by bors"}], "milestone": null, "draft": false, "commits_url": "https://api.github.com/repos/rust-lang/rust/pulls/68448/commits", "review_comments_url": "https://api.github.com/repos/rust-lang/rust/pulls/68448/comments", "review_comment_url": "https://api.github.com/repos/rust-lang/rust/pulls/comments{/number}", "comments_url": "https://api.github.com/repos/rust-lang/rust/issues/68448/comments", "statuses_url": "https://api.github.com/repos/rust-lang/rust/statuses/72aaa3a414d17aa0c4f19feafa5bab5f84b60e63", "head": {"label": "maurer:dyn-cdylib", "ref": "dyn-cdylib", "sha": "72aaa3a414d17aa0c4f19feafa5bab5f84b60e63", "user": {"login": "maurer", "id": 136037, "node_id": "MDQ6VXNlcjEzNjAzNw==", "avatar_url": "https://avatars.githubusercontent.com/u/136037?v=4", "gravatar_id": "", "url": "https://api.github.com/users/maurer", "html_url": "https://github.com/maurer", "followers_url": "https://api.github.com/users/maurer/followers", "following_url": "https://api.github.com/users/maurer/following{/other_user}", "gists_url": "https://api.github.com/users/maurer/gists{/gist_id}", "starred_url": "https://api.github.com/users/maurer/starred{/owner}{/repo}", "subscriptions_url": "https://api.github.com/users/maurer/subscriptions", "organizations_url": "https://api.github.com/users/maurer/orgs", "repos_url": "https://api.github.com/users/maurer/repos", "events_url": "https://api.github.com/users/maurer/events{/privacy}", "received_events_url": "https://api.github.com/users/maurer/received_events", "type": "User", "site_admin": false}, "repo": {"id": 147701128, "node_id": "MDEwOlJlcG9zaXRvcnkxNDc3MDExMjg=", "name": "rust", "full_name": "maurer/rust", "private": false, "owner": {"login": "maurer", "id": 136037, "node_id": "MDQ6VXNlcjEzNjAzNw==", "avatar_url": "https://avatars.githubusercontent.com/u/136037?v=4", "gravatar_id": "", "url": "https://api.github.com/users/maurer", "html_url": "https://github.com/maurer", "followers_url": "https://api.github.com/users/maurer/followers", "following_url": "https://api.github.com/users/maurer/following{/other_user}", "gists_url": "https://api.github.com/users/maurer/gists{/gist_id}", "starred_url": "https://api.github.com/users/maurer/starred{/owner}{/repo}", "subscriptions_url": "https://api.github.com/users/maurer/subscriptions", "organizations_url": "https://api.github.com/users/maurer/orgs", "repos_url": "https://api.github.com/users/maurer/repos", "events_url": "https://api.github.com/users/maurer/events{/privacy}", "received_events_url": "https://api.github.com/users/maurer/received_events", "type": "User", "site_admin": false}, "html_url": "https://github.com/maurer/rust", "description": "A safe, concurrent, practical language.", "fork": true, "url": "https://api.github.com/repos/maurer/rust", "forks_url": "https://api.github.com/repos/maurer/rust/forks", "keys_url": "https://api.github.com/repos/maurer/rust/keys{/key_id}", "collaborators_url": "https://api.github.com/repos/maurer/rust/collaborators{/collaborator}", "teams_url": "https://api.github.com/repos/maurer/rust/teams", "hooks_url": "https://api.github.com/repos/maurer/rust/hooks", "issue_events_url": "https://api.github.com/repos/maurer/rust/issues/events{/number}", "events_url": "https://api.github.com/repos/maurer/rust/events", "assignees_url": "https://api.github.com/repos/maurer/rust/assignees{/user}", "branches_url": "https://api.github.com/repos/maurer/rust/branches{/branch}", "tags_url": "https://api.github.com/repos/maurer/rust/tags", "blobs_url": "https://api.github.com/repos/maurer/rust/git/blobs{/sha}", "git_tags_url": "https://api.github.com/repos/maurer/rust/git/tags{/sha}", "git_refs_url": "https://api.github.com/repos/maurer/rust/git/refs{/sha}", "trees_url": "https://api.github.com/repos/maurer/rust/git/trees{/sha}", "statuses_url": "https://api.github.com/repos/maurer/rust/statuses/{sha}", "languages_url": "https://api.github.com/repos/maurer/rust/languages", "stargazers_url": "https://api.github.com/repos/maurer/rust/stargazers", "contributors_url": "https://api.github.com/repos/maurer/rust/contributors", "subscribers_url": "https://api.github.com/repos/maurer/rust/subscribers", "subscription_url": "https://api.github.com/repos/maurer/rust/subscription", "commits_url": "https://api.github.com/repos/maurer/rust/commits{/sha}", "git_commits_url": "https://api.github.com/repos/maurer/rust/git/commits{/sha}", "comments_url": "https://api.github.com/repos/maurer/rust/comments{/number}", "issue_comment_url": "https://api.github.com/repos/maurer/rust/issues/comments{/number}", "contents_url": "https://api.github.com/repos/maurer/rust/contents/{+path}", "compare_url": "https://api.github.com/repos/maurer/rust/compare/{base}...{head}", "merges_url": "https://api.github.com/repos/maurer/rust/merges", "archive_url": "https://api.github.com/repos/maurer/rust/{archive_format}{/ref}", "downloads_url": "https://api.github.com/repos/maurer/rust/downloads", "issues_url": "https://api.github.com/repos/maurer/rust/issues{/number}", "pulls_url": "https://api.github.com/repos/maurer/rust/pulls{/number}", "milestones_url": "https://api.github.com/repos/maurer/rust/milestones{/number}", "notifications_url": "https://api.github.com/repos/maurer/rust/notifications{?since,all,participating}", "labels_url": "https://api.github.com/repos/maurer/rust/labels{/name}", "releases_url": "https://api.github.com/repos/maurer/rust/releases{/id}", "deployments_url": "https://api.github.com/repos/maurer/rust/deployments", "created_at": "2018-09-06T16:20:11Z", "updated_at": "2023-03-08T23:25:38Z", "pushed_at": "2023-03-08T23:41:59Z", "git_url": "git://github.com/maurer/rust.git", "ssh_url": "git@github.com:maurer/rust.git", "clone_url": "https://github.com/maurer/rust.git", "svn_url": "https://github.com/maurer/rust", "homepage": "https://www.rust-lang.org", "size": 1079063, "stargazers_count": 0, "watchers_count": 0, "language": "Rust", "has_issues": false, "has_projects": true, "has_downloads": true, "has_wiki": false, "has_pages": false, "has_discussions": false, "forks_count": 0, "mirror_url": null, "archived": false, "disabled": false, "open_issues_count": 0, "license": {"key": "other", "name": "Other", "spdx_id": "NOASSERTION", "url": null, "node_id": "MDc6TGljZW5zZTA="}, "allow_forking": true, "is_template": false, "web_commit_signoff_required": false, "topics": [], "visibility": "public", "forks": 0, "open_issues": 0, "watchers": 0, "default_branch": "master"}}, "base": {"label": "rust-lang:master", "ref": "master", "sha": "e0bbe7915e2b663ac84244918d6d06e0747ed33e", "user": {"login": "rust-lang", "id": 5430905, "node_id": "MDEyOk9yZ2FuaXphdGlvbjU0MzA5MDU=", "avatar_url": "https://avatars.githubusercontent.com/u/5430905?v=4", "gravatar_id": "", "url": "https://api.github.com/users/rust-lang", "html_url": "https://github.com/rust-lang", "followers_url": "https://api.github.com/users/rust-lang/followers", "following_url": "https://api.github.com/users/rust-lang/following{/other_user}", "gists_url": "https://api.github.com/users/rust-lang/gists{/gist_id}", "starred_url": "https://api.github.com/users/rust-lang/starred{/owner}{/repo}", "subscriptions_url": "https://api.github.com/users/rust-lang/subscriptions", "organizations_url": "https://api.github.com/users/rust-lang/orgs", "repos_url": "https://api.github.com/users/rust-lang/repos", "events_url": "https://api.github.com/users/rust-lang/events{/privacy}", "received_events_url": "https://api.github.com/users/rust-lang/received_events", "type": "Organization", "site_admin": false}, "repo": {"id": 724712, "node_id": "MDEwOlJlcG9zaXRvcnk3MjQ3MTI=", "name": "rust", "full_name": "rust-lang/rust", "private": false, "owner": {"login": "rust-lang", "id": 5430905, "node_id": "MDEyOk9yZ2FuaXphdGlvbjU0MzA5MDU=", "avatar_url": "https://avatars.githubusercontent.com/u/5430905?v=4", "gravatar_id": "", "url": "https://api.github.com/users/rust-lang", "html_url": "https://github.com/rust-lang", "followers_url": "https://api.github.com/users/rust-lang/followers", "following_url": "https://api.github.com/users/rust-lang/following{/other_user}", "gists_url": "https://api.github.com/users/rust-lang/gists{/gist_id}", "starred_url": "https://api.github.com/users/rust-lang/starred{/owner}{/repo}", "subscriptions_url": "https://api.github.com/users/rust-lang/subscriptions", "organizations_url": "https://api.github.com/users/rust-lang/orgs", "repos_url": "https://api.github.com/users/rust-lang/repos", "events_url": "https://api.github.com/users/rust-lang/events{/privacy}", "received_events_url": "https://api.github.com/users/rust-lang/received_events", "type": "Organization", "site_admin": false}, "html_url": "https://github.com/rust-lang/rust", "description": "Empowering everyone to build reliable and efficient software.", "fork": false, "url": "https://api.github.com/repos/rust-lang/rust", "forks_url": "https://api.github.com/repos/rust-lang/rust/forks", "keys_url": "https://api.github.com/repos/rust-lang/rust/keys{/key_id}", "collaborators_url": "https://api.github.com/repos/rust-lang/rust/collaborators{/collaborator}", "teams_url": "https://api.github.com/repos/rust-lang/rust/teams", "hooks_url": "https://api.github.com/repos/rust-lang/rust/hooks", "issue_events_url": "https://api.github.com/repos/rust-lang/rust/issues/events{/number}", "events_url": "https://api.github.com/repos/rust-lang/rust/events", "assignees_url": "https://api.github.com/repos/rust-lang/rust/assignees{/user}", "branches_url": "https://api.github.com/repos/rust-lang/rust/branches{/branch}", "tags_url": "https://api.github.com/repos/rust-lang/rust/tags", "blobs_url": "https://api.github.com/repos/rust-lang/rust/git/blobs{/sha}", "git_tags_url": "https://api.github.com/repos/rust-lang/rust/git/tags{/sha}", "git_refs_url": "https://api.github.com/repos/rust-lang/rust/git/refs{/sha}", "trees_url": "https://api.github.com/repos/rust-lang/rust/git/trees{/sha}", "statuses_url": "https://api.github.com/repos/rust-lang/rust/statuses/{sha}", "languages_url": "https://api.github.com/repos/rust-lang/rust/languages", "stargazers_url": "https://api.github.com/repos/rust-lang/rust/stargazers", "contributors_url": "https://api.github.com/repos/rust-lang/rust/contributors", "subscribers_url": "https://api.github.com/repos/rust-lang/rust/subscribers", "subscription_url": "https://api.github.com/repos/rust-lang/rust/subscription", "commits_url": "https://api.github.com/repos/rust-lang/rust/commits{/sha}", "git_commits_url": "https://api.github.com/repos/rust-lang/rust/git/commits{/sha}", "comments_url": "https://api.github.com/repos/rust-lang/rust/comments{/number}", "issue_comment_url": "https://api.github.com/repos/rust-lang/rust/issues/comments{/number}", "contents_url": "https://api.github.com/repos/rust-lang/rust/contents/{+path}", "compare_url": "https://api.github.com/repos/rust-lang/rust/compare/{base}...{head}", "merges_url": "https://api.github.com/repos/rust-lang/rust/merges", "archive_url": "https://api.github.com/repos/rust-lang/rust/{archive_format}{/ref}", "downloads_url": "https://api.github.com/repos/rust-lang/rust/downloads", "issues_url": "https://api.github.com/repos/rust-lang/rust/issues{/number}", "pulls_url": "https://api.github.com/repos/rust-lang/rust/pulls{/number}", "milestones_url": "https://api.github.com/repos/rust-lang/rust/milestones{/number}", "notifications_url": "https://api.github.com/repos/rust-lang/rust/notifications{?since,all,participating}", "labels_url": "https://api.github.com/repos/rust-lang/rust/labels{/name}", "releases_url": "https://api.github.com/repos/rust-lang/rust/releases{/id}", "deployments_url": "https://api.github.com/repos/rust-lang/rust/deployments", "created_at": "2010-06-16T20:39:03Z", "updated_at": "2023-06-20T02:32:08Z", "pushed_at": "2023-06-20T02:02:30Z", "git_url": "git://github.com/rust-lang/rust.git", "ssh_url": "git@github.com:rust-lang/rust.git", "clone_url": "https://github.com/rust-lang/rust.git", "svn_url": "https://github.com/rust-lang/rust", "homepage": "https://www.rust-lang.org", "size": 930398, "stargazers_count": 82760, "watchers_count": 82760, "language": "Rust", "has_issues": true, "has_projects": true, "has_downloads": true, "has_wiki": false, "has_pages": false, "has_discussions": false, "forks_count": 10961, "mirror_url": null, "archived": false, "disabled": false, "open_issues_count": 9626, "license": {"key": "other", "name": "Other", "spdx_id": "NOASSERTION", "url": null, "node_id": "MDc6TGljZW5zZTA="}, "allow_forking": true, "is_template": false, "web_commit_signoff_required": false, "topics": ["compiler", "hacktoberfest", "language", "rust"], "visibility": "public", "forks": 10961, "open_issues": 9626, "watchers": 82760, "default_branch": "master"}}, "_links": {"self": {"href": "https://api.github.com/repos/rust-lang/rust/pulls/68448"}, "html": {"href": "https://github.com/rust-lang/rust/pull/68448"}, "issue": {"href": "https://api.github.com/repos/rust-lang/rust/issues/68448"}, "comments": {"href": "https://api.github.com/repos/rust-lang/rust/issues/68448/comments"}, "review_comments": {"href": "https://api.github.com/repos/rust-lang/rust/pulls/68448/comments"}, "review_comment": {"href": "https://api.github.com/repos/rust-lang/rust/pulls/comments{/number}"}, "commits": {"href": "https://api.github.com/repos/rust-lang/rust/pulls/68448/commits"}, "statuses": {"href": "https://api.github.com/repos/rust-lang/rust/statuses/72aaa3a414d17aa0c4f19feafa5bab5f84b60e63"}}, "author_association": "CONTRIBUTOR", "auto_merge": null, "active_lock_reason": null, "merged": true, "mergeable": null, "rebaseable": null, "mergeable_state": "unknown", "merged_by": {"login": "bors", "id": 3372342, "node_id": "MDQ6VXNlcjMzNzIzNDI=", "avatar_url": "https://avatars.githubusercontent.com/u/3372342?v=4", "gravatar_id": "", "url": "https://api.github.com/users/bors", "html_url": "https://github.com/bors", "followers_url": "https://api.github.com/users/bors/followers", "following_url": "https://api.github.com/users/bors/following{/other_user}", "gists_url": "https://api.github.com/users/bors/gists{/gist_id}", "starred_url": "https://api.github.com/users/bors/starred{/owner}{/repo}", "subscriptions_url": "https://api.github.com/users/bors/subscriptions", "organizations_url": "https://api.github.com/users/bors/orgs", "repos_url": "https://api.github.com/users/bors/repos", "events_url": "https://api.github.com/users/bors/events{/privacy}", "received_events_url": "https://api.github.com/users/bors/received_events", "type": "User", "site_admin": false}, "comments": 12, "review_comments": 0, "maintainer_can_modify": false, "commits": 1, "additions": 66, "deletions": 24, "changed_files": 8}