{"sha": "35214d3c6cd5f70b38baa6d879ca40d9db8118ba", "node_id": "MDY6Q29tbWl0NzI0NzEyOjM1MjE0ZDNjNmNkNWY3MGIzOGJhYTZkODc5Y2E0MGQ5ZGI4MTE4YmE=", "commit": {"author": {"name": "Young-il Choi", "email": "duddlf.choi@samsung.com", "date": "2013-05-03T15:46:52Z"}, "committer": {"name": "Young-il Choi", "email": "duddlf.choi@samsung.com", "date": "2013-05-03T15:46:52Z"}, "message": "configure: CFG_ADB for adb added", "tree": {"sha": "2f16f32dfe7dff04e702ceb5d2af660a723582f9", "url": "https://api.github.com/repos/rust-lang/rust/git/trees/2f16f32dfe7dff04e702ceb5d2af660a723582f9"}, "url": "https://api.github.com/repos/rust-lang/rust/git/commits/35214d3c6cd5f70b38baa6d879ca40d9db8118ba", "comment_count": 0, "verification": {"verified": false, "reason": "unsigned", "signature": null, "payload": null}}, "url": "https://api.github.com/repos/rust-lang/rust/commits/35214d3c6cd5f70b38baa6d879ca40d9db8118ba", "html_url": "https://github.com/rust-lang/rust/commit/35214d3c6cd5f70b38baa6d879ca40d9db8118ba", "comments_url": "https://api.github.com/repos/rust-lang/rust/commits/35214d3c6cd5f70b38baa6d879ca40d9db8118ba/comments", "author": {"login": "yichoi", "id": 3222276, "node_id": "MDQ6VXNlcjMyMjIyNzY=", "avatar_url": "https://avatars.githubusercontent.com/u/3222276?v=4", "gravatar_id": "", "url": "https://api.github.com/users/yichoi", "html_url": "https://github.com/yichoi", "followers_url": "https://api.github.com/users/yichoi/followers", "following_url": "https://api.github.com/users/yichoi/following{/other_user}", "gists_url": "https://api.github.com/users/yichoi/gists{/gist_id}", "starred_url": "https://api.github.com/users/yichoi/starred{/owner}{/repo}", "subscriptions_url": "https://api.github.com/users/yichoi/subscriptions", "organizations_url": "https://api.github.com/users/yichoi/orgs", "repos_url": "https://api.github.com/users/yichoi/repos", "events_url": "https://api.github.com/users/yichoi/events{/privacy}", "received_events_url": "https://api.github.com/users/yichoi/received_events", "type": "User", "site_admin": false}, "committer": {"login": "yichoi", "id": 3222276, "node_id": "MDQ6VXNlcjMyMjIyNzY=", "avatar_url": "https://avatars.githubusercontent.com/u/3222276?v=4", "gravatar_id": "", "url": "https://api.github.com/users/yichoi", "html_url": "https://github.com/yichoi", "followers_url": "https://api.github.com/users/yichoi/followers", "following_url": "https://api.github.com/users/yichoi/following{/other_user}", "gists_url": "https://api.github.com/users/yichoi/gists{/gist_id}", "starred_url": "https://api.github.com/users/yichoi/starred{/owner}{/repo}", "subscriptions_url": "https://api.github.com/users/yichoi/subscriptions", "organizations_url": "https://api.github.com/users/yichoi/orgs", "repos_url": "https://api.github.com/users/yichoi/repos", "events_url": "https://api.github.com/users/yichoi/events{/privacy}", "received_events_url": "https://api.github.com/users/yichoi/received_events", "type": "User", "site_admin": false}, "parents": [{"sha": "17b368fd2225ffc65333a9a5293fca4f6bdcf7f5", "url": "https://api.github.com/repos/rust-lang/rust/commits/17b368fd2225ffc65333a9a5293fca4f6bdcf7f5", "html_url": "https://github.com/rust-lang/rust/commit/17b368fd2225ffc65333a9a5293fca4f6bdcf7f5"}], "stats": {"total": 4, "additions": 4, "deletions": 0}, "files": [{"sha": "0c4afa0566de33541b187a1b16917a4fa420a8d0", "filename": "configure", "status": "modified", "additions": 4, "deletions": 0, "changes": 4, "blob_url": "https://github.com/rust-lang/rust/blob/35214d3c6cd5f70b38baa6d879ca40d9db8118ba/configure", "raw_url": "https://github.com/rust-lang/rust/raw/35214d3c6cd5f70b38baa6d879ca40d9db8118ba/configure", "contents_url": "https://api.github.com/repos/rust-lang/rust/contents/configure?ref=35214d3c6cd5f70b38baa6d879ca40d9db8118ba", "patch": "@@ -439,6 +439,10 @@ then\n     probe CFG_ZCAT             zcat\n fi\n \n+step_msg \"looking for target specific programs\"\n+\n+probe CFG_ADB        adb\n+\n if [ ! -z \"$CFG_PANDOC\" ]\n then\n     PV_MAJOR_MINOR=$(pandoc --version | grep '^pandoc ' |"}]}