{"sha": "a5839662f448602d6aa2d724432844fc2d08947e", "node_id": "MDY6Q29tbWl0NzI0NzEyOmE1ODM5NjYyZjQ0ODYwMmQ2YWEyZDcyNDQzMjg0NGZjMmQwODk0N2U=", "commit": {"author": {"name": "Edwin Cheng", "email": "edwin0cheng@gmail.com", "date": "2019-11-04T17:16:06Z"}, "committer": {"name": "Edwin Cheng", "email": "edwin0cheng@gmail.com", "date": "2019-11-04T17:16:06Z"}, "message": "Change to  add 1 if non zero shift", "tree": {"sha": "1453254be75301226f9b911043f72802257dcc61", "url": "https://api.github.com/repos/rust-lang/rust/git/trees/1453254be75301226f9b911043f72802257dcc61"}, "url": "https://api.github.com/repos/rust-lang/rust/git/commits/a5839662f448602d6aa2d724432844fc2d08947e", "comment_count": 0, "verification": {"verified": false, "reason": "unsigned", "signature": null, "payload": null}}, "url": "https://api.github.com/repos/rust-lang/rust/commits/a5839662f448602d6aa2d724432844fc2d08947e", "html_url": "https://github.com/rust-lang/rust/commit/a5839662f448602d6aa2d724432844fc2d08947e", "comments_url": "https://api.github.com/repos/rust-lang/rust/commits/a5839662f448602d6aa2d724432844fc2d08947e/comments", "author": {"login": "edwin0cheng", "id": 11014119, "node_id": "MDQ6VXNlcjExMDE0MTE5", "avatar_url": "https://avatars.githubusercontent.com/u/11014119?v=4", "gravatar_id": "", "url": "https://api.github.com/users/edwin0cheng", "html_url": "https://github.com/edwin0cheng", "followers_url": "https://api.github.com/users/edwin0cheng/followers", "following_url": "https://api.github.com/users/edwin0cheng/following{/other_user}", "gists_url": "https://api.github.com/users/edwin0cheng/gists{/gist_id}", "starred_url": "https://api.github.com/users/edwin0cheng/starred{/owner}{/repo}", "subscriptions_url": "https://api.github.com/users/edwin0cheng/subscriptions", "organizations_url": "https://api.github.com/users/edwin0cheng/orgs", "repos_url": "https://api.github.com/users/edwin0cheng/repos", "events_url": "https://api.github.com/users/edwin0cheng/events{/privacy}", "received_events_url": "https://api.github.com/users/edwin0cheng/received_events", "type": "User", "site_admin": false}, "committer": {"login": "edwin0cheng", "id": 11014119, "node_id": "MDQ6VXNlcjExMDE0MTE5", "avatar_url": "https://avatars.githubusercontent.com/u/11014119?v=4", "gravatar_id": "", "url": "https://api.github.com/users/edwin0cheng", "html_url": "https://github.com/edwin0cheng", "followers_url": "https://api.github.com/users/edwin0cheng/followers", "following_url": "https://api.github.com/users/edwin0cheng/following{/other_user}", "gists_url": "https://api.github.com/users/edwin0cheng/gists{/gist_id}", "starred_url": "https://api.github.com/users/edwin0cheng/starred{/owner}{/repo}", "subscriptions_url": "https://api.github.com/users/edwin0cheng/subscriptions", "organizations_url": "https://api.github.com/users/edwin0cheng/orgs", "repos_url": "https://api.github.com/users/edwin0cheng/repos", "events_url": "https://api.github.com/users/edwin0cheng/events{/privacy}", "received_events_url": "https://api.github.com/users/edwin0cheng/received_events", "type": "User", "site_admin": false}, "parents": [{"sha": "188a1412b9d21ead5d823ce3ca00d3b4f823221b", "url": "https://api.github.com/repos/rust-lang/rust/commits/188a1412b9d21ead5d823ce3ca00d3b4f823221b", "html_url": "https://github.com/rust-lang/rust/commit/188a1412b9d21ead5d823ce3ca00d3b4f823221b"}], "stats": {"total": 2, "additions": 1, "deletions": 1}, "files": [{"sha": "15f000175559d8581c3cfed09e7b16f91e71d641", "filename": "crates/ra_mbe/src/lib.rs", "status": "modified", "additions": 1, "deletions": 1, "changes": 2, "blob_url": "https://github.com/rust-lang/rust/blob/a5839662f448602d6aa2d724432844fc2d08947e/crates%2Fra_mbe%2Fsrc%2Flib.rs", "raw_url": "https://github.com/rust-lang/rust/raw/a5839662f448602d6aa2d724432844fc2d08947e/crates%2Fra_mbe%2Fsrc%2Flib.rs", "contents_url": "https://api.github.com/repos/rust-lang/rust/contents/crates%2Fra_mbe%2Fsrc%2Flib.rs?ref=a5839662f448602d6aa2d724432844fc2d08947e", "patch": "@@ -108,7 +108,7 @@ impl MacroRules {\n \n         // Note that TokenId is started from zero,\n         // We have to add 1 to prevent duplication.\n-        let shift = max_id(tt).unwrap_or(0) + 1;\n+        let shift = max_id(tt).map_or(0, |it| it + 1);\n         Ok(MacroRules { rules, shift })\n     }\n "}]}