{"sha": "af001677d103a3e0f5cf1bfde44982171faf34b9", "node_id": "MDY6Q29tbWl0NzI0NzEyOmFmMDAxNjc3ZDEwM2EzZTBmNWNmMWJmZGU0NDk4MjE3MWZhZjM0Yjk=", "commit": {"author": {"name": "Edwin Cheng", "email": "edwin0cheng@gmail.com", "date": "2020-05-04T16:17:30Z"}, "committer": {"name": "Edwin Cheng", "email": "edwin0cheng@gmail.com", "date": "2020-05-04T16:17:30Z"}, "message": "Fix test", "tree": {"sha": "715ea587d2bdf4b667700dddefe0adbc8cbeb736", "url": "https://api.github.com/repos/rust-lang/rust/git/trees/715ea587d2bdf4b667700dddefe0adbc8cbeb736"}, "url": "https://api.github.com/repos/rust-lang/rust/git/commits/af001677d103a3e0f5cf1bfde44982171faf34b9", "comment_count": 0, "verification": {"verified": false, "reason": "unsigned", "signature": null, "payload": null}}, "url": "https://api.github.com/repos/rust-lang/rust/commits/af001677d103a3e0f5cf1bfde44982171faf34b9", "html_url": "https://github.com/rust-lang/rust/commit/af001677d103a3e0f5cf1bfde44982171faf34b9", "comments_url": "https://api.github.com/repos/rust-lang/rust/commits/af001677d103a3e0f5cf1bfde44982171faf34b9/comments", "author": {"login": "edwin0cheng", "id": 11014119, "node_id": "MDQ6VXNlcjExMDE0MTE5", "avatar_url": "https://avatars.githubusercontent.com/u/11014119?v=4", "gravatar_id": "", "url": "https://api.github.com/users/edwin0cheng", "html_url": "https://github.com/edwin0cheng", "followers_url": "https://api.github.com/users/edwin0cheng/followers", "following_url": "https://api.github.com/users/edwin0cheng/following{/other_user}", "gists_url": "https://api.github.com/users/edwin0cheng/gists{/gist_id}", "starred_url": "https://api.github.com/users/edwin0cheng/starred{/owner}{/repo}", "subscriptions_url": "https://api.github.com/users/edwin0cheng/subscriptions", "organizations_url": "https://api.github.com/users/edwin0cheng/orgs", "repos_url": "https://api.github.com/users/edwin0cheng/repos", "events_url": "https://api.github.com/users/edwin0cheng/events{/privacy}", "received_events_url": "https://api.github.com/users/edwin0cheng/received_events", "type": "User", "site_admin": false}, "committer": {"login": "edwin0cheng", "id": 11014119, "node_id": "MDQ6VXNlcjExMDE0MTE5", "avatar_url": "https://avatars.githubusercontent.com/u/11014119?v=4", "gravatar_id": "", "url": "https://api.github.com/users/edwin0cheng", "html_url": "https://github.com/edwin0cheng", "followers_url": "https://api.github.com/users/edwin0cheng/followers", "following_url": "https://api.github.com/users/edwin0cheng/following{/other_user}", "gists_url": "https://api.github.com/users/edwin0cheng/gists{/gist_id}", "starred_url": "https://api.github.com/users/edwin0cheng/starred{/owner}{/repo}", "subscriptions_url": "https://api.github.com/users/edwin0cheng/subscriptions", "organizations_url": "https://api.github.com/users/edwin0cheng/orgs", "repos_url": "https://api.github.com/users/edwin0cheng/repos", "events_url": "https://api.github.com/users/edwin0cheng/events{/privacy}", "received_events_url": "https://api.github.com/users/edwin0cheng/received_events", "type": "User", "site_admin": false}, "parents": [{"sha": "8d96db3417fdabb1bad7a9919ea8ae1db25296f1", "url": "https://api.github.com/repos/rust-lang/rust/commits/8d96db3417fdabb1bad7a9919ea8ae1db25296f1", "html_url": "https://github.com/rust-lang/rust/commit/8d96db3417fdabb1bad7a9919ea8ae1db25296f1"}], "stats": {"total": 32, "additions": 16, "deletions": 16}, "files": [{"sha": "40289e3ca529c035817c549b3c9bed5a09b3d5fe", "filename": "crates/ra_hir_def/src/nameres/tests/macros.rs", "status": "modified", "additions": 16, "deletions": 16, "changes": 32, "blob_url": "https://github.com/rust-lang/rust/blob/af001677d103a3e0f5cf1bfde44982171faf34b9/crates%2Fra_hir_def%2Fsrc%2Fnameres%2Ftests%2Fmacros.rs", "raw_url": "https://github.com/rust-lang/rust/raw/af001677d103a3e0f5cf1bfde44982171faf34b9/crates%2Fra_hir_def%2Fsrc%2Fnameres%2Ftests%2Fmacros.rs", "contents_url": "https://api.github.com/repos/rust-lang/rust/contents/crates%2Fra_hir_def%2Fsrc%2Fnameres%2Ftests%2Fmacros.rs?ref=af001677d103a3e0f5cf1bfde44982171faf34b9", "patch": "@@ -19,12 +19,12 @@ fn macro_rules_are_globally_visible() {\n     );\n     assert_snapshot!(map, @r###\"\n    \u22eecrate\n-   \u22eeFoo: t v\n+   \u22eeFoo: t\n    \u22eenested: t\n    \u22ee\n    \u22eecrate::nested\n-   \u22eeBar: t v\n-   \u22eeBaz: t v\n+   \u22eeBar: t\n+   \u22eeBaz: t\n     \"###);\n }\n \n@@ -91,13 +91,13 @@ fn macro_rules_from_other_crates_are_visible() {\n     );\n     assert_snapshot!(map, @r###\"\n    \u22eecrate\n-   \u22eeBar: t v\n-   \u22eeFoo: t v\n+   \u22eeBar: t\n+   \u22eeFoo: t\n    \u22eebar: t\n    \u22ee\n    \u22eecrate::bar\n-   \u22eeBar: t v\n-   \u22eeFoo: t v\n+   \u22eeBar: t\n+   \u22eeFoo: t\n    \u22eebar: t\n     \"###);\n }\n@@ -124,13 +124,13 @@ fn macro_rules_export_with_local_inner_macros_are_visible() {\n     );\n     assert_snapshot!(map, @r###\"\n    \u22eecrate\n-   \u22eeBar: t v\n-   \u22eeFoo: t v\n+   \u22eeBar: t\n+   \u22eeFoo: t\n    \u22eebar: t\n    \u22ee\n    \u22eecrate::bar\n-   \u22eeBar: t v\n-   \u22eeFoo: t v\n+   \u22eeBar: t\n+   \u22eeFoo: t\n    \u22eebar: t\n     \"###);\n }\n@@ -161,13 +161,13 @@ fn local_inner_macros_makes_local_macros_usable() {\n     );\n     assert_snapshot!(map, @r###\"\n    \u22eecrate\n-   \u22eeBar: t v\n-   \u22eeFoo: t v\n+   \u22eeBar: t\n+   \u22eeFoo: t\n    \u22eebar: t\n    \u22ee\n    \u22eecrate::bar\n-   \u22eeBar: t v\n-   \u22eeFoo: t v\n+   \u22eeBar: t\n+   \u22eeFoo: t\n    \u22eebar: t\n     \"###);\n }\n@@ -204,7 +204,7 @@ fn unexpanded_macro_should_expand_by_fixedpoint_loop() {\n     );\n     assert_snapshot!(map, @r###\"\n    \u22eecrate\n-   \u22eeFoo: t v\n+   \u22eeFoo: t\n    \u22eebar: m\n    \u22eefoo: m\n     \"###);"}]}