{"sha": "d54f9dc75cf3e9405ff56240c685eb7cf994c26e", "node_id": "MDY6Q29tbWl0NzI0NzEyOmQ1NGY5ZGM3NWNmM2U5NDA1ZmY1NjI0MGM2ODVlYjdjZjk5NGMyNmU=", "commit": {"author": {"name": "Timo", "email": "timorcb@gmail.com", "date": "2019-03-31T15:05:14Z"}, "committer": {"name": "timotree3", "email": "timorcb@gmail.com", "date": "2019-03-31T15:33:41Z"}, "message": "README: Update to RalfJung's suggestion...\n\n...verbatim. Thanks :)", "tree": {"sha": "856739ab929c276ae561aae6990e75c48e012a89", "url": "https://api.github.com/repos/rust-lang/rust/git/trees/856739ab929c276ae561aae6990e75c48e012a89"}, "url": "https://api.github.com/repos/rust-lang/rust/git/commits/d54f9dc75cf3e9405ff56240c685eb7cf994c26e", "comment_count": 0, "verification": {"verified": false, "reason": "unsigned", "signature": null, "payload": null}}, "url": "https://api.github.com/repos/rust-lang/rust/commits/d54f9dc75cf3e9405ff56240c685eb7cf994c26e", "html_url": "https://github.com/rust-lang/rust/commit/d54f9dc75cf3e9405ff56240c685eb7cf994c26e", "comments_url": "https://api.github.com/repos/rust-lang/rust/commits/d54f9dc75cf3e9405ff56240c685eb7cf994c26e/comments", "author": {"login": "timotree3", "id": 6473438, "node_id": "MDQ6VXNlcjY0NzM0Mzg=", "avatar_url": "https://avatars.githubusercontent.com/u/6473438?v=4", "gravatar_id": "", "url": "https://api.github.com/users/timotree3", "html_url": "https://github.com/timotree3", "followers_url": "https://api.github.com/users/timotree3/followers", "following_url": "https://api.github.com/users/timotree3/following{/other_user}", "gists_url": "https://api.github.com/users/timotree3/gists{/gist_id}", "starred_url": "https://api.github.com/users/timotree3/starred{/owner}{/repo}", "subscriptions_url": "https://api.github.com/users/timotree3/subscriptions", "organizations_url": "https://api.github.com/users/timotree3/orgs", "repos_url": "https://api.github.com/users/timotree3/repos", "events_url": "https://api.github.com/users/timotree3/events{/privacy}", "received_events_url": "https://api.github.com/users/timotree3/received_events", "type": "User", "site_admin": false}, "committer": {"login": "timotree3", "id": 6473438, "node_id": "MDQ6VXNlcjY0NzM0Mzg=", "avatar_url": "https://avatars.githubusercontent.com/u/6473438?v=4", "gravatar_id": "", "url": "https://api.github.com/users/timotree3", "html_url": "https://github.com/timotree3", "followers_url": "https://api.github.com/users/timotree3/followers", "following_url": "https://api.github.com/users/timotree3/following{/other_user}", "gists_url": "https://api.github.com/users/timotree3/gists{/gist_id}", "starred_url": "https://api.github.com/users/timotree3/starred{/owner}{/repo}", "subscriptions_url": "https://api.github.com/users/timotree3/subscriptions", "organizations_url": "https://api.github.com/users/timotree3/orgs", "repos_url": "https://api.github.com/users/timotree3/repos", "events_url": "https://api.github.com/users/timotree3/events{/privacy}", "received_events_url": "https://api.github.com/users/timotree3/received_events", "type": "User", "site_admin": false}, "parents": [{"sha": "67e123502c50dd2c24c34ff6886233d6721cfb5a", "url": "https://api.github.com/repos/rust-lang/rust/commits/67e123502c50dd2c24c34ff6886233d6721cfb5a", "html_url": "https://github.com/rust-lang/rust/commit/67e123502c50dd2c24c34ff6886233d6721cfb5a"}], "stats": {"total": 10, "additions": 1, "deletions": 9}, "files": [{"sha": "a366e433b0f39cbef5186db86f98bffb32962569", "filename": "README.md", "status": "modified", "additions": 1, "deletions": 9, "changes": 10, "blob_url": "https://github.com/rust-lang/rust/blob/d54f9dc75cf3e9405ff56240c685eb7cf994c26e/README.md", "raw_url": "https://github.com/rust-lang/rust/raw/d54f9dc75cf3e9405ff56240c685eb7cf994c26e/README.md", "contents_url": "https://api.github.com/repos/rust-lang/rust/contents/README.md?ref=d54f9dc75cf3e9405ff56240c685eb7cf994c26e", "patch": "@@ -53,15 +53,7 @@ Install Miri via `rustup`:\n rustup component add miri\n ```\n \n-### error: component 'miri' is unavailable for download (nightly)\n-\n-The development of rustc's internals is quite fast paced. Downstream projects that rely on nightly internals, particularly clippy, can break fairly often because of this.\n-\n-When such breakages occur the nightly release will be missing Miri. This is a trade-off compared with the other option of just not publishing the night's release, but does avoid blocking the rust nightly releases for people that don't need clippy/Miri.\n-\n-To mitigate the issues we have:\n-* rustup will warn if the update is missing any components you currently have. This means you can no longer accidentally update to a no-Miri release. Once Miri is available again it'll update.\n-* However, if you need latest nightly Miri you can use <https://rust-lang.github.io/rustup-components-history/> to find and install a dated nightly release e.g. `rustup install nightly-2018-12-06`.\n+If `rustup` says the `miri` component is unavailable, that's because not all nightly releases come with all tools. Check out this website to determine a nightly version that comes with Miri and install that, e.g. using `rustup install nightly-2019-03-28`.\n \n Now you can run your project in Miri:\n "}]}