{"sha": "4d2cf7156f52f377023a842613d13d8271607aa0", "node_id": "MDY6Q29tbWl0MTM2NTMxMDA6NGQyY2Y3MTU2ZjUyZjM3NzAyM2E4NDI2MTNkMTNkODI3MTYwN2FhMA==", "commit": {"author": {"name": "Nick Clifton", "email": "nickc@redhat.com", "date": "2001-03-02T22:21:24Z"}, "committer": {"name": "Nick Clifton", "email": "nickc@gcc.gnu.org", "date": "2001-03-02T22:21:24Z"}, "message": "Remove RCS ident strings to allow comparisions with multiple source checkouts to work\n\nFrom-SVN: r40195", "tree": {"sha": "a55d2eb3ce428f7f254d36eb17dbf77952fbed63", "url": "https://api.github.com/repos/Rust-GCC/gccrs/git/trees/a55d2eb3ce428f7f254d36eb17dbf77952fbed63"}, "url": "https://api.github.com/repos/Rust-GCC/gccrs/git/commits/4d2cf7156f52f377023a842613d13d8271607aa0", "comment_count": 0, "verification": {"verified": false, "reason": "unsigned", "signature": null, "payload": null}}, "url": "https://api.github.com/repos/Rust-GCC/gccrs/commits/4d2cf7156f52f377023a842613d13d8271607aa0", "html_url": "https://github.com/Rust-GCC/gccrs/commit/4d2cf7156f52f377023a842613d13d8271607aa0", "comments_url": "https://api.github.com/repos/Rust-GCC/gccrs/commits/4d2cf7156f52f377023a842613d13d8271607aa0/comments", "author": {"login": "nickclifton", "id": 31441682, "node_id": "MDQ6VXNlcjMxNDQxNjgy", "avatar_url": "https://avatars.githubusercontent.com/u/31441682?v=4", "gravatar_id": "", "url": "https://api.github.com/users/nickclifton", "html_url": "https://github.com/nickclifton", "followers_url": "https://api.github.com/users/nickclifton/followers", "following_url": "https://api.github.com/users/nickclifton/following{/other_user}", "gists_url": "https://api.github.com/users/nickclifton/gists{/gist_id}", "starred_url": "https://api.github.com/users/nickclifton/starred{/owner}{/repo}", "subscriptions_url": "https://api.github.com/users/nickclifton/subscriptions", "organizations_url": "https://api.github.com/users/nickclifton/orgs", "repos_url": "https://api.github.com/users/nickclifton/repos", "events_url": "https://api.github.com/users/nickclifton/events{/privacy}", "received_events_url": "https://api.github.com/users/nickclifton/received_events", "type": "User", "site_admin": false}, "committer": null, "parents": [{"sha": "f11fc7bfa49bac623388b22258071c80eab7d16f", "url": "https://api.github.com/repos/Rust-GCC/gccrs/commits/f11fc7bfa49bac623388b22258071c80eab7d16f", "html_url": "https://github.com/Rust-GCC/gccrs/commit/f11fc7bfa49bac623388b22258071c80eab7d16f"}], "stats": {"total": 57, "additions": 21, "deletions": 36}, "files": [{"sha": "88c6332d3fe356ce86096cea4dc5a9b826286642", "filename": "libffi/ChangeLog", "status": "modified", "additions": 21, "deletions": 0, "changes": 21, "blob_url": "https://github.com/Rust-GCC/gccrs/blob/4d2cf7156f52f377023a842613d13d8271607aa0/libffi%2FChangeLog", "raw_url": "https://github.com/Rust-GCC/gccrs/raw/4d2cf7156f52f377023a842613d13d8271607aa0/libffi%2FChangeLog", "contents_url": "https://api.github.com/repos/Rust-GCC/gccrs/contents/libffi%2FChangeLog?ref=4d2cf7156f52f377023a842613d13d8271607aa0", "patch": "@@ -1,3 +1,24 @@\n+2001-03-02  Nick Clifton  <nickc@redhat.com>\n+\n+\t* include/ffi.h.in: Remove RCS ident string.\n+\t* include/ffi_mips.h: Remove RCS ident string.\n+\t* src/debug.c: Remove RCS ident string.\n+\t* src/ffitest.c: Remove RCS ident string.\n+\t* src/prep_cif.c: Remove RCS ident string.\n+\t* src/types.c: Remove RCS ident string.\n+\t* src/alpha/ffi.c: Remove RCS ident string.\n+\t* src/alpha/osf.S: Remove RCS ident string.\n+\t* src/arm/ffi.c: Remove RCS ident string.\n+\t* src/arm/sysv.S: Remove RCS ident string.\n+\t* src/mips/ffi.c: Remove RCS ident string.\n+\t* src/mips/n32.S: Remove RCS ident string.\n+\t* src/mips/o32.S: Remove RCS ident string.\n+\t* src/sparc/ffi.c: Remove RCS ident string.\n+\t* src/sparc/v8.S: Remove RCS ident string.\n+\t* src/sparc/v9.S: Remove RCS ident string.\n+\t* src/x86/ffi.c: Remove RCS ident string.\n+\t* src/x86/sysv.S: Remove RCS ident string.\n+\n 2001-02-08  Joseph S. Myers  <jsm28@cam.ac.uk>\n \n \t* include/ffi.h.in: Change sourceware.cygnus.com references to"}, {"sha": "17c383d3167d22aaafea8bbf15ec092b3527c797", "filename": "libffi/include/ffi.h.in", "status": "modified", "additions": 0, "deletions": 2, "changes": 2, "blob_url": "https://github.com/Rust-GCC/gccrs/blob/4d2cf7156f52f377023a842613d13d8271607aa0/libffi%2Finclude%2Fffi.h.in", "raw_url": "https://github.com/Rust-GCC/gccrs/raw/4d2cf7156f52f377023a842613d13d8271607aa0/libffi%2Finclude%2Fffi.h.in", "contents_url": "https://api.github.com/repos/Rust-GCC/gccrs/contents/libffi%2Finclude%2Fffi.h.in?ref=4d2cf7156f52f377023a842613d13d8271607aa0", "patch": "@@ -1,8 +1,6 @@\n /* -----------------------------------------------------------------*-C-*-\n    libffi @VERSION@ - Copyright (c) 1996-1999  Cygnus Solutions\n \n-   $Id: ffi.h.in,v 1.6 2000/12/08 19:41:15 green Exp $\n-\n    Permission is hereby granted, free of charge, to any person obtaining\n    a copy of this software and associated documentation files (the\n    ``Software''), to deal in the Software without restriction, including"}, {"sha": "6fd56474f069603d5ee82051e5218af3b15781b2", "filename": "libffi/include/ffi_mips.h", "status": "modified", "additions": 0, "deletions": 2, "changes": 2, "blob_url": "https://github.com/Rust-GCC/gccrs/blob/4d2cf7156f52f377023a842613d13d8271607aa0/libffi%2Finclude%2Fffi_mips.h", "raw_url": "https://github.com/Rust-GCC/gccrs/raw/4d2cf7156f52f377023a842613d13d8271607aa0/libffi%2Finclude%2Fffi_mips.h", "contents_url": "https://api.github.com/repos/Rust-GCC/gccrs/contents/libffi%2Finclude%2Fffi_mips.h?ref=4d2cf7156f52f377023a842613d13d8271607aa0", "patch": "@@ -3,8 +3,6 @@\n    \n    MIPS FFI Definitions\n \n-   $Id: ffi_mips.h,v 1.1.1.1 1998/11/29 16:48:16 green Exp $\n-\n    Permission is hereby granted, free of charge, to any person obtaining\n    a copy of this software and associated documentation files (the\n    ``Software''), to deal in the Software without restriction, including"}, {"sha": "a0becb3b37865fd90b18477e5fc740c10613baf4", "filename": "libffi/src/alpha/ffi.c", "status": "modified", "additions": 0, "deletions": 2, "changes": 2, "blob_url": "https://github.com/Rust-GCC/gccrs/blob/4d2cf7156f52f377023a842613d13d8271607aa0/libffi%2Fsrc%2Falpha%2Fffi.c", "raw_url": "https://github.com/Rust-GCC/gccrs/raw/4d2cf7156f52f377023a842613d13d8271607aa0/libffi%2Fsrc%2Falpha%2Fffi.c", "contents_url": "https://api.github.com/repos/Rust-GCC/gccrs/contents/libffi%2Fsrc%2Falpha%2Fffi.c?ref=4d2cf7156f52f377023a842613d13d8271607aa0", "patch": "@@ -3,8 +3,6 @@\n    \n    Alpha Foreign Function Interface \n \n-   $Id: ffi.c,v 1.1.1.1 1998/11/29 16:48:16 green Exp $\n-\n    Permission is hereby granted, free of charge, to any person obtaining\n    a copy of this software and associated documentation files (the\n    ``Software''), to deal in the Software without restriction, including"}, {"sha": "b3dc477fec043222df3f99260c7c30405fed6dd5", "filename": "libffi/src/alpha/osf.S", "status": "modified", "additions": 0, "deletions": 2, "changes": 2, "blob_url": "https://github.com/Rust-GCC/gccrs/blob/4d2cf7156f52f377023a842613d13d8271607aa0/libffi%2Fsrc%2Falpha%2Fosf.S", "raw_url": "https://github.com/Rust-GCC/gccrs/raw/4d2cf7156f52f377023a842613d13d8271607aa0/libffi%2Fsrc%2Falpha%2Fosf.S", "contents_url": "https://api.github.com/repos/Rust-GCC/gccrs/contents/libffi%2Fsrc%2Falpha%2Fosf.S?ref=4d2cf7156f52f377023a842613d13d8271607aa0", "patch": "@@ -3,8 +3,6 @@\n    \n    Alpha/OSF Foreign Function Interface \n \n-   $Id: osf.S,v 1.1.1.1 1998/11/29 16:48:16 green Exp $\n-\n    Permission is hereby granted, free of charge, to any person obtaining\n    a copy of this software and associated documentation files (the\n    ``Software''), to deal in the Software without restriction, including"}, {"sha": "0ede742e53c0e182a700c0ae50306e5fc6611b95", "filename": "libffi/src/arm/ffi.c", "status": "modified", "additions": 0, "deletions": 2, "changes": 2, "blob_url": "https://github.com/Rust-GCC/gccrs/blob/4d2cf7156f52f377023a842613d13d8271607aa0/libffi%2Fsrc%2Farm%2Fffi.c", "raw_url": "https://github.com/Rust-GCC/gccrs/raw/4d2cf7156f52f377023a842613d13d8271607aa0/libffi%2Fsrc%2Farm%2Fffi.c", "contents_url": "https://api.github.com/repos/Rust-GCC/gccrs/contents/libffi%2Fsrc%2Farm%2Fffi.c?ref=4d2cf7156f52f377023a842613d13d8271607aa0", "patch": "@@ -3,8 +3,6 @@\n    \n    ARM Foreign Function Interface \n \n-   $Id: ffi.c,v 1.1.1.1 1998/11/29 16:48:16 green Exp $\n-\n    Permission is hereby granted, free of charge, to any person obtaining\n    a copy of this software and associated documentation files (the\n    ``Software''), to deal in the Software without restriction, including"}, {"sha": "84744d77562156564ea390abb72d6d4e06d2e40e", "filename": "libffi/src/arm/sysv.S", "status": "modified", "additions": 0, "deletions": 2, "changes": 2, "blob_url": "https://github.com/Rust-GCC/gccrs/blob/4d2cf7156f52f377023a842613d13d8271607aa0/libffi%2Fsrc%2Farm%2Fsysv.S", "raw_url": "https://github.com/Rust-GCC/gccrs/raw/4d2cf7156f52f377023a842613d13d8271607aa0/libffi%2Fsrc%2Farm%2Fsysv.S", "contents_url": "https://api.github.com/repos/Rust-GCC/gccrs/contents/libffi%2Fsrc%2Farm%2Fsysv.S?ref=4d2cf7156f52f377023a842613d13d8271607aa0", "patch": "@@ -3,8 +3,6 @@\n    \n    ARM Foreign Function Interface \n \n-   $Id: sysv.S,v 1.1.1.1 1998/11/29 16:48:16 green Exp $\n-\n    Permission is hereby granted, free of charge, to any person obtaining\n    a copy of this software and associated documentation files (the\n    ``Software''), to deal in the Software without restriction, including"}, {"sha": "099b39778257d3730c0614b822c7c1667d8c298a", "filename": "libffi/src/debug.c", "status": "modified", "additions": 0, "deletions": 2, "changes": 2, "blob_url": "https://github.com/Rust-GCC/gccrs/blob/4d2cf7156f52f377023a842613d13d8271607aa0/libffi%2Fsrc%2Fdebug.c", "raw_url": "https://github.com/Rust-GCC/gccrs/raw/4d2cf7156f52f377023a842613d13d8271607aa0/libffi%2Fsrc%2Fdebug.c", "contents_url": "https://api.github.com/repos/Rust-GCC/gccrs/contents/libffi%2Fsrc%2Fdebug.c?ref=4d2cf7156f52f377023a842613d13d8271607aa0", "patch": "@@ -1,8 +1,6 @@\n /* -----------------------------------------------------------------------\n    debug.c - Copyright (c) 1996 Cygnus Solutions\n \n-   $Id: debug.c,v 1.1.1.1 1998/11/29 16:48:16 green Exp $\n-\n    Permission is hereby granted, free of charge, to any person obtaining\n    a copy of this software and associated documentation files (the\n    ``Software''), to deal in the Software without restriction, including"}, {"sha": "e1b1cdaca0d2d6c01dc755aaa36d090f833a2d5a", "filename": "libffi/src/ffitest.c", "status": "modified", "additions": 0, "deletions": 2, "changes": 2, "blob_url": "https://github.com/Rust-GCC/gccrs/blob/4d2cf7156f52f377023a842613d13d8271607aa0/libffi%2Fsrc%2Fffitest.c", "raw_url": "https://github.com/Rust-GCC/gccrs/raw/4d2cf7156f52f377023a842613d13d8271607aa0/libffi%2Fsrc%2Fffitest.c", "contents_url": "https://api.github.com/repos/Rust-GCC/gccrs/contents/libffi%2Fsrc%2Fffitest.c?ref=4d2cf7156f52f377023a842613d13d8271607aa0", "patch": "@@ -1,8 +1,6 @@\n /* -----------------------------------------------------------------------\n    ffitest.c - Copyright (c) 1996, 1997, 1998  Cygnus Solutions\n \n-   $Id: ffitest.c,v 1.1.1.1 1998/11/29 16:48:16 green Exp $\n-\n    Permission is hereby granted, free of charge, to any person obtaining\n    a copy of this software and associated documentation files (the\n    ``Software''), to deal in the Software without restriction, including"}, {"sha": "ca3971fe6f6582d8a362b211f2ebae5154f7f1fa", "filename": "libffi/src/mips/ffi.c", "status": "modified", "additions": 0, "deletions": 2, "changes": 2, "blob_url": "https://github.com/Rust-GCC/gccrs/blob/4d2cf7156f52f377023a842613d13d8271607aa0/libffi%2Fsrc%2Fmips%2Fffi.c", "raw_url": "https://github.com/Rust-GCC/gccrs/raw/4d2cf7156f52f377023a842613d13d8271607aa0/libffi%2Fsrc%2Fmips%2Fffi.c", "contents_url": "https://api.github.com/repos/Rust-GCC/gccrs/contents/libffi%2Fsrc%2Fmips%2Fffi.c?ref=4d2cf7156f52f377023a842613d13d8271607aa0", "patch": "@@ -3,8 +3,6 @@\n    \n    MIPS Foreign Function Interface \n \n-   $Id: ffi.c,v 1.1.1.1 1998/11/29 16:48:16 green Exp $\n-\n    Permission is hereby granted, free of charge, to any person obtaining\n    a copy of this software and associated documentation files (the\n    ``Software''), to deal in the Software without restriction, including"}, {"sha": "04b5e40b41f1f5bfb411a16471a007fb16f8eee8", "filename": "libffi/src/mips/n32.S", "status": "modified", "additions": 0, "deletions": 2, "changes": 2, "blob_url": "https://github.com/Rust-GCC/gccrs/blob/4d2cf7156f52f377023a842613d13d8271607aa0/libffi%2Fsrc%2Fmips%2Fn32.S", "raw_url": "https://github.com/Rust-GCC/gccrs/raw/4d2cf7156f52f377023a842613d13d8271607aa0/libffi%2Fsrc%2Fmips%2Fn32.S", "contents_url": "https://api.github.com/repos/Rust-GCC/gccrs/contents/libffi%2Fsrc%2Fmips%2Fn32.S?ref=4d2cf7156f52f377023a842613d13d8271607aa0", "patch": "@@ -3,8 +3,6 @@\n    \n    MIPS Foreign Function Interface \n \n-   $Id: n32.S,v 1.1.1.1 1998/11/29 16:48:16 green Exp $\n-\n    Permission is hereby granted, free of charge, to any person obtaining\n    a copy of this software and associated documentation files (the\n    ``Software''), to deal in the Software without restriction, including"}, {"sha": "4dfb2ba21048b93cb8241df6587b5e26a7bb01b0", "filename": "libffi/src/mips/o32.S", "status": "modified", "additions": 0, "deletions": 2, "changes": 2, "blob_url": "https://github.com/Rust-GCC/gccrs/blob/4d2cf7156f52f377023a842613d13d8271607aa0/libffi%2Fsrc%2Fmips%2Fo32.S", "raw_url": "https://github.com/Rust-GCC/gccrs/raw/4d2cf7156f52f377023a842613d13d8271607aa0/libffi%2Fsrc%2Fmips%2Fo32.S", "contents_url": "https://api.github.com/repos/Rust-GCC/gccrs/contents/libffi%2Fsrc%2Fmips%2Fo32.S?ref=4d2cf7156f52f377023a842613d13d8271607aa0", "patch": "@@ -3,8 +3,6 @@\n    \n    MIPS Foreign Function Interface \n \n-   $Id: o32.S,v 1.1.1.1 1998/11/29 16:48:16 green Exp $\n-\n    Permission is hereby granted, free of charge, to any person obtaining\n    a copy of this software and associated documentation files (the\n    ``Software''), to deal in the Software without restriction, including"}, {"sha": "d53981af7b125de3b11c0d8a61a752a99be41832", "filename": "libffi/src/prep_cif.c", "status": "modified", "additions": 0, "deletions": 2, "changes": 2, "blob_url": "https://github.com/Rust-GCC/gccrs/blob/4d2cf7156f52f377023a842613d13d8271607aa0/libffi%2Fsrc%2Fprep_cif.c", "raw_url": "https://github.com/Rust-GCC/gccrs/raw/4d2cf7156f52f377023a842613d13d8271607aa0/libffi%2Fsrc%2Fprep_cif.c", "contents_url": "https://api.github.com/repos/Rust-GCC/gccrs/contents/libffi%2Fsrc%2Fprep_cif.c?ref=4d2cf7156f52f377023a842613d13d8271607aa0", "patch": "@@ -1,8 +1,6 @@\n /* -----------------------------------------------------------------------\n    prep_cif.c - Copyright (c) 1996, 1998  Cygnus Solutions\n \n-   $Id: prep_cif.c,v 1.1.1.1 1998/11/29 16:48:16 green Exp $\n-\n    Permission is hereby granted, free of charge, to any person obtaining\n    a copy of this software and associated documentation files (the\n    ``Software''), to deal in the Software without restriction, including"}, {"sha": "f557013a4b4afdd29850376372ec8272550ac3b0", "filename": "libffi/src/sparc/ffi.c", "status": "modified", "additions": 0, "deletions": 2, "changes": 2, "blob_url": "https://github.com/Rust-GCC/gccrs/blob/4d2cf7156f52f377023a842613d13d8271607aa0/libffi%2Fsrc%2Fsparc%2Fffi.c", "raw_url": "https://github.com/Rust-GCC/gccrs/raw/4d2cf7156f52f377023a842613d13d8271607aa0/libffi%2Fsrc%2Fsparc%2Fffi.c", "contents_url": "https://api.github.com/repos/Rust-GCC/gccrs/contents/libffi%2Fsrc%2Fsparc%2Fffi.c?ref=4d2cf7156f52f377023a842613d13d8271607aa0", "patch": "@@ -3,8 +3,6 @@\n    \n    Sparc Foreign Function Interface \n \n-   $Id: ffi.c,v 1.1.1.1 1998/11/29 16:48:16 green Exp $\n-\n    Permission is hereby granted, free of charge, to any person obtaining\n    a copy of this software and associated documentation files (the\n    ``Software''), to deal in the Software without restriction, including"}, {"sha": "0357f4de7d7b770046e20e7c17767017690d21f9", "filename": "libffi/src/sparc/v8.S", "status": "modified", "additions": 0, "deletions": 2, "changes": 2, "blob_url": "https://github.com/Rust-GCC/gccrs/blob/4d2cf7156f52f377023a842613d13d8271607aa0/libffi%2Fsrc%2Fsparc%2Fv8.S", "raw_url": "https://github.com/Rust-GCC/gccrs/raw/4d2cf7156f52f377023a842613d13d8271607aa0/libffi%2Fsrc%2Fsparc%2Fv8.S", "contents_url": "https://api.github.com/repos/Rust-GCC/gccrs/contents/libffi%2Fsrc%2Fsparc%2Fv8.S?ref=4d2cf7156f52f377023a842613d13d8271607aa0", "patch": "@@ -3,8 +3,6 @@\n    \n    Sparc Foreign Function Interface \n \n-   $Id: v8.S,v 1.1.1.1 1998/11/29 16:48:16 green Exp $\n-\n    Permission is hereby granted, free of charge, to any person obtaining\n    a copy of this software and associated documentation files (the\n    ``Software''), to deal in the Software without restriction, including"}, {"sha": "c937f439304ff367d621c6ad9954cac741b9a8a7", "filename": "libffi/src/sparc/v9.S", "status": "modified", "additions": 0, "deletions": 2, "changes": 2, "blob_url": "https://github.com/Rust-GCC/gccrs/blob/4d2cf7156f52f377023a842613d13d8271607aa0/libffi%2Fsrc%2Fsparc%2Fv9.S", "raw_url": "https://github.com/Rust-GCC/gccrs/raw/4d2cf7156f52f377023a842613d13d8271607aa0/libffi%2Fsrc%2Fsparc%2Fv9.S", "contents_url": "https://api.github.com/repos/Rust-GCC/gccrs/contents/libffi%2Fsrc%2Fsparc%2Fv9.S?ref=4d2cf7156f52f377023a842613d13d8271607aa0", "patch": "@@ -3,8 +3,6 @@\n    \n    Sparc 64bit Foreign Function Interface \n \n-   $Id:$\n-\n    Permission is hereby granted, free of charge, to any person obtaining\n    a copy of this software and associated documentation files (the\n    ``Software''), to deal in the Software without restriction, including"}, {"sha": "57488c91eab0e6ab812a6eb4c11b6505bbcab193", "filename": "libffi/src/types.c", "status": "modified", "additions": 0, "deletions": 2, "changes": 2, "blob_url": "https://github.com/Rust-GCC/gccrs/blob/4d2cf7156f52f377023a842613d13d8271607aa0/libffi%2Fsrc%2Ftypes.c", "raw_url": "https://github.com/Rust-GCC/gccrs/raw/4d2cf7156f52f377023a842613d13d8271607aa0/libffi%2Fsrc%2Ftypes.c", "contents_url": "https://api.github.com/repos/Rust-GCC/gccrs/contents/libffi%2Fsrc%2Ftypes.c?ref=4d2cf7156f52f377023a842613d13d8271607aa0", "patch": "@@ -3,8 +3,6 @@\n    \n    Predefined ffi_types needed by libffi.\n \n-   $Id: types.c,v 1.1.1.1 1998/11/29 16:48:16 green Exp $\n-\n    Permission is hereby granted, free of charge, to any person obtaining\n    a copy of this software and associated documentation files (the\n    ``Software''), to deal in the Software without restriction, including"}, {"sha": "162d66fc84b01ffb3b766316ca3b24da2a882f78", "filename": "libffi/src/x86/ffi.c", "status": "modified", "additions": 0, "deletions": 2, "changes": 2, "blob_url": "https://github.com/Rust-GCC/gccrs/blob/4d2cf7156f52f377023a842613d13d8271607aa0/libffi%2Fsrc%2Fx86%2Fffi.c", "raw_url": "https://github.com/Rust-GCC/gccrs/raw/4d2cf7156f52f377023a842613d13d8271607aa0/libffi%2Fsrc%2Fx86%2Fffi.c", "contents_url": "https://api.github.com/repos/Rust-GCC/gccrs/contents/libffi%2Fsrc%2Fx86%2Fffi.c?ref=4d2cf7156f52f377023a842613d13d8271607aa0", "patch": "@@ -3,8 +3,6 @@\n    \n    x86 Foreign Function Interface \n \n-   $Id: ffi.c,v 1.3 1999/08/08 13:05:12 green Exp $\n-\n    Permission is hereby granted, free of charge, to any person obtaining\n    a copy of this software and associated documentation files (the\n    ``Software''), to deal in the Software without restriction, including"}, {"sha": "d59a16433bf22ba1ec6d16ac53e8b378d998e31f", "filename": "libffi/src/x86/sysv.S", "status": "modified", "additions": 0, "deletions": 2, "changes": 2, "blob_url": "https://github.com/Rust-GCC/gccrs/blob/4d2cf7156f52f377023a842613d13d8271607aa0/libffi%2Fsrc%2Fx86%2Fsysv.S", "raw_url": "https://github.com/Rust-GCC/gccrs/raw/4d2cf7156f52f377023a842613d13d8271607aa0/libffi%2Fsrc%2Fx86%2Fsysv.S", "contents_url": "https://api.github.com/repos/Rust-GCC/gccrs/contents/libffi%2Fsrc%2Fx86%2Fsysv.S?ref=4d2cf7156f52f377023a842613d13d8271607aa0", "patch": "@@ -3,8 +3,6 @@\n    \n    X86 Foreign Function Interface \n \n-   $Id: sysv.S,v 1.2 1999/08/04 18:00:05 green Exp $\n-\n    Permission is hereby granted, free of charge, to any person obtaining\n    a copy of this software and associated documentation files (the\n    ``Software''), to deal in the Software without restriction, including"}]}