{"sha": "c6e087c59c02378da1957dc4dc353aed177e8169", "node_id": "MDY6Q29tbWl0MTM2NTMxMDA6YzZlMDg3YzU5YzAyMzc4ZGExOTU3ZGM0ZGMzNTNhZWQxNzdlODE2OQ==", "commit": {"author": {"name": "Doug Evans", "email": "dje@gnu.org", "date": "1996-06-10T19:52:08Z"}, "committer": {"name": "Doug Evans", "email": "dje@gnu.org", "date": "1996-06-10T19:52:08Z"}, "message": "Makefile (pexecute.o): Add rule.\n\n\t* Makefile (pexecute.o): Add rule.\n\t(xgcc): Link in pexecute.o.\n\t(protoize,unprotoize): Likewise.\n\nFrom-SVN: r12268", "tree": {"sha": "c14070e0a07d4d5ffa39dc4c8dd96e9766d00494", "url": "https://api.github.com/repos/Rust-GCC/gccrs/git/trees/c14070e0a07d4d5ffa39dc4c8dd96e9766d00494"}, "url": "https://api.github.com/repos/Rust-GCC/gccrs/git/commits/c6e087c59c02378da1957dc4dc353aed177e8169", "comment_count": 0, "verification": {"verified": false, "reason": "unsigned", "signature": null, "payload": null}}, "url": "https://api.github.com/repos/Rust-GCC/gccrs/commits/c6e087c59c02378da1957dc4dc353aed177e8169", "html_url": "https://github.com/Rust-GCC/gccrs/commit/c6e087c59c02378da1957dc4dc353aed177e8169", "comments_url": "https://api.github.com/repos/Rust-GCC/gccrs/commits/c6e087c59c02378da1957dc4dc353aed177e8169/comments", "author": null, "committer": null, "parents": [{"sha": "b0e878721209b1b2a6f6596a9334178884167f2e", "url": "https://api.github.com/repos/Rust-GCC/gccrs/commits/b0e878721209b1b2a6f6596a9334178884167f2e", "html_url": "https://github.com/Rust-GCC/gccrs/commit/b0e878721209b1b2a6f6596a9334178884167f2e"}], "stats": {"total": 19, "additions": 12, "deletions": 7}, "files": [{"sha": "0ff304c4d2b6e8347255bf0e02401c698a6f301d", "filename": "gcc/Makefile.in", "status": "modified", "additions": 12, "deletions": 7, "changes": 19, "blob_url": "https://github.com/Rust-GCC/gccrs/blob/c6e087c59c02378da1957dc4dc353aed177e8169/gcc%2FMakefile.in", "raw_url": "https://github.com/Rust-GCC/gccrs/raw/c6e087c59c02378da1957dc4dc353aed177e8169/gcc%2FMakefile.in", "contents_url": "https://api.github.com/repos/Rust-GCC/gccrs/contents/gcc%2FMakefile.in?ref=c6e087c59c02378da1957dc4dc353aed177e8169", "patch": "@@ -688,9 +688,9 @@ stamp-objlist: Makefile $(OBJS) $(BC_OBJS)\n # We call this executable `xgcc' rather than `gcc'\n # to avoid confusion if the current directory is in the path\n # and CC is `gcc'.  It is renamed to `gcc' when it is installed.\n-xgcc: gcc.o version.o choose-temp.o $(LIBDEPS) $(EXTRA_GCC_OBJS)\n-\t$(CC) $(ALL_CFLAGS) $(LDFLAGS) -o $@ gcc.o version.o choose-temp.o \\\n-\t  $(EXTRA_GCC_OBJS) $(LIBS)\n+xgcc: gcc.o version.o choose-temp.o pexecute.o $(LIBDEPS) $(EXTRA_GCC_OBJS)\n+\t$(CC) $(ALL_CFLAGS) $(LDFLAGS) -o $@ gcc.o version.o \\\n+\t  choose-temp.o pexecute.o $(EXTRA_GCC_OBJS) $(LIBS)\n \n # Dump a specs file to make -B./ read these specs over installed ones.\n specs: xgcc\n@@ -1177,6 +1177,7 @@ dumpvers: dumpvers.c\n version.o: version.c\n obstack.o: obstack.c\n choose-temp.o: choose-temp.c\n+pexecute.o: pexecute.c\n \n convert.o: convert.c $(CONFIG_H) $(TREE_H) flags.h convert.h\n \n@@ -1687,14 +1688,18 @@ cppalloc.o: cppalloc.c $(CONFIG_H)\n \n proto: config.status protoize unprotoize SYSCALLS.c.X\n \n-protoize: protoize.o getopt.o getopt1.o getpwd.o version.o $(LIBDEPS)\n+protoize: protoize.o getopt.o getopt1.o getpwd.o version.o \\\n+    pexecute.o choose-temp.o $(LIBDEPS)\n \t$(CC) $(ALL_CFLAGS) $(LDFLAGS) -o $@ \\\n-\t  protoize.o getopt.o getopt1.o getpwd.o version.o $(LIBS)\n+\t  protoize.o getopt.o getopt1.o getpwd.o version.o \\\n+\t  pexecute.o choose-temp.o $(LIBS)\n protoize.o: stamp-proto ; @true\n \n-unprotoize: unprotoize.o getopt.o getopt1.o getpwd.o version.o $(LIBDEPS)\n+unprotoize: unprotoize.o getopt.o getopt1.o getpwd.o version.o \\\n+    pexecute.o choose-temp.o $(LIBDEPS)\n \t$(CC) $(ALL_CFLAGS) $(LDFLAGS) -o $@ \\\n-\t  unprotoize.o getopt.o getopt1.o getpwd.o version.o $(LIBS)\n+\t  unprotoize.o getopt.o getopt1.o getpwd.o version.o \\\n+\t  pexecute.o choose-temp.o $(LIBS)\n unprotoize.o:\tstamp-proto ; @true\n \n stamp-proto: protoize.c getopt.h $(CONFIG_H)"}]}